tdotly/__init__.py
tdotly/tly.py
tdotly-1.0a1.dev3.dist-info/METADATA
tdotly-1.0a1.dev3.dist-info/WHEEL
tdotly-1.0a1.dev3.dist-info/licenses/LICENSE
tdotly-1.0a1.dev3.dist-info/RECORD
