Metadata-Version: 2.1
Name: tdotly
Version: 1.0a1.dev3
Summary: This is a python package for t.ly url shortener service.
Project-URL: Homepage, https://github.com/PriomDeb/tdotly
Project-URL: Bug Tracker, https://github.com/PriomDeb/tdotly/issues
Author-email: Priom Deb <priom@priomdeb.com>
License: MIT License
Classifier: License :: OSI Approved :: MIT License
Classifier: Operating System :: OS Independent
Classifier: Programming Language :: Python :: 3
Requires-Python: >=3.7
Requires-Dist: requests==2.28.1
